et_api/common/SortBy.py
et_api/common/SortOrder.py
et_api/common/__init__.py
et_api/v1/Client.py
et_api/v1/__init__.py
et_api/v1/endpoints/Domain.py
et_api/v1/endpoints/IP.py
et_api/v1/endpoints/ReputationCategories.py
et_api/v1/endpoints/Sample.py
et_api/v1/endpoints/Sid.py
et_api/v1/endpoints/__init__.py
et_api/v1/filters/IPFilter.py
et_api/v1/filters/__init__.py
et_api/v1/resources/CategoryInfo.py
et_api/v1/resources/ConnectionInfo.py
et_api/v1/resources/DNSInfo.py
et_api/v1/resources/DomainInfo.py
et_api/v1/resources/EventInfo.py
et_api/v1/resources/GeoInfo.py
et_api/v1/resources/HTTPInfo.py
et_api/v1/resources/IDSEventInfo.py
et_api/v1/resources/IPInfo.py
et_api/v1/resources/IPInfoEx.py
et_api/v1/resources/MalwareInfo.py
et_api/v1/resources/NameServerInfo.py
et_api/v1/resources/ReputationInfo.py
et_api/v1/resources/SampleInfo.py
et_api/v1/resources/SidDocInfo.py
et_api/v1/resources/SigIPInfo.py
et_api/v1/resources/SigInfo.py
et_api/v1/resources/SigNameInfo.py
et_api/v1/resources/SigRefInfo.py
et_api/v1/resources/Whois.py
et_api/v1/resources/WhoisRegistrant.py
et_api/v1/resources/WhoisRegistrar.py
et_api/v1/resources/__init__.py
et_api/web/Collection.py
et_api/web/CollectionResource.py
et_api/web/Dictionary.py
et_api/web/DictionaryCollection.py
et_api/web/DictionaryResource.py
et_api/web/ErrorHandler.py
et_api/web/FilterOptions.py
et_api/web/Resource.py
et_api/web/Resources.py
et_api/web/__init__.py
et_api-1.0.2.dist-info/LICENSE
et_api-1.0.2.dist-info/METADATA
et_api-1.0.2.dist-info/WHEEL
et_api-1.0.2.dist-info/top_level.txt
et_api-1.0.2.dist-info/RECORD
