Metadata-Version: 2.1
Name: et-api
Version: 1.0.2
Summary: Proofpoint Emerging Threats Python API Package
License: MIT
Project-URL: repository, https://github.com/pfptcommunity/et-api-python
Project-URL: homepage, https://apidocs.emergingthreats.net
Requires-Python: >3.9
License-File: LICENSE
Requires-Dist: requests
Requires-Dist: pysocks
